{"status":"OK","copyright":"Copyright (c) 2017 The New York Times Company.  All Rights Reserved.","num_results":55,"results":{"bestsellers_date":"2017-04-22","published_date":"2017-05-07","published_date_description":"latest","previous_published_date":"2017-04-30","next_published_date":"","lists":[{"list_id":704,"list_name":"Combined Print and E-Book Fiction","list_name_encoded":"combined-print-and-e-book-fiction","display_name":"Combined Print & E-Book Fiction","updated":"WEEKLY","list_image":"https:\/\/s1.nyt.com\/du\/books\/images\/9781455586561.jpg","list_image_width":330,"list_image_height":480,"books":[{"age_group":"","amazon_product_url":"https:\/\/www.amazon.com\/Fix-Amos-Decker-David-Baldacci\/dp\/1455586560?tag=thenewyorktim-20","article_chapter_link":"","author":"David Baldacci","book_image":"https:\/\/s1.nyt.com\/du\/books\/images\/9781455586561.jpg","book_image_width":330,"book_image_height":480,"book_review_link":"","contributor":"by David Baldacci","contributor_note":"","created_date":"2017-04-27 16:00:11","description":"The detective Amos Decker (\u201cMemory Man\u201d) witnesses a murder-suicide that turns out to be a matter of national security.","first_chapter_link":"","price":0,"primary_isbn10":"1455586552","primary_isbn13":"9781455586554","publisher":"Grand Central","rank":1,"rank_last_week":0,"sunday_review_link":"","title":"THE FIX","updated_date":"2017-04-27 21:00:13","weeks_on_list":1,"buy_links":[{"name":"Local Booksellers","url":"http:\/\/www.indiebound.org\/book\/9781455586554?aff=NYT"},{"name":"Barnes and Noble","url":"http:\/\/www.anrdoezrs.net\/click-7990613-11819508?url=http%3A%2F%2Fwww.barnesandnoble.com%2Fw%2F%3Fean%3D9781455586554"},{"name":"Amazon","url":"https:\/\/www.amazon.com\/Fix-Amos-Decker-David-Baldacci\/dp\/1455586560?tag=thenewyorktim-20"}]},{"age_group":"","amazon_product_url":"https:\/\/www.amazon.com\/Fast-Loose-Stone-Barrington-Novel-ebook\/dp\/B01J2STXC6?tag=thenewyorktim-20","article_chapter_link":"","author":"Stuart Woods","book_image":"https:\/\/s1.nyt.com\/du\/books\/images\/9780399574214.jpg","book_image_width":328,"book_image_height":495,"book_review_link":"","contributor":"by Stuart Woods","contributor_note":"","created_date":"2017-04-27 16:00:11","description":"In the 41st Stone Barrington novel, the New York attorney acquires a ruthless, hot-headed enemy.","first_chapter_link":"","price":0,"primary_isbn10":"0399574212","primary_isbn13":"9780399574214","publisher":"Putnam","rank":2,"rank_last_week":0,"sunday_review_link":"","title":"FAST AND LOOSE","updated_date":"2017-04-27 21:00:13","weeks_on_list":1,"buy_links":[{"name":"Local Booksellers","url":"http:\/\/www.indiebound.org\/book\/9780399574214?aff=NYT"},{"name":"Barnes and Noble","url":"http:\/\/www.anrdoezrs.net\/click-7990613-11819508?url=http%3A%2F%2Fwww.barnesandnoble.com%2Fw%2F%3Fean%3D9780399574214"},{"name":"Amazon","url":"https:\/\/www.amazon.com\/Fast-Loose-Stone-Barrington-Novel-ebook\/dp\/B01J2STXC6?tag=thenewyorktim-20"}]},{"age_group":"","amazon_product_url":"https:\/\/www.amazon.com\/Black-Book-James-Patterson-ebook\/dp\/B01HZFB38U?tag=thenewyorktim-20","article_chapter_link":"","author":"James Patterson and David Ellis","book_image":"https:\/\/s1.nyt.com\/du\/books\/images\/9780316464147.jpg","book_image_width":321,"book_image_height":495,"book_review_link":"","contributor":"by James Patterson and David Ellis","contributor_note":"","created_date":"2017-04-27 16:00:11","description":"After a raid on a brothel that serviced Chicago\u2019s elite, two people are dead and the madam\u2019s black book has disappeared. Who is responsible?","first_chapter_link":"","price":0,"primary_isbn10":"0316464147","primary_isbn13":"9780316464147","publisher":"Little, Brown","rank":3,"rank_last_week":1,"sunday_review_link":"","title":"THE BLACK BOOK","updated_date":"2017-04-27 21:00:13","weeks_on_list":4,"buy_links":[{"name":"Local Booksellers","url":"http:\/\/www.indiebound.org\/book\/9780316464147?aff=NYT"},{"name":"Barnes and Noble","url":"http:\/\/www.anrdoezrs.net\/click-7990613-11819508?url=http%3A%2F%2Fwww.barnesandnoble.com%2Fw%2F%3Fean%3D9780316464147"},{"name":"Amazon","url":"https:\/\/www.amazon.com\/Black-Book-James-Patterson-ebook\/dp\/B01HZFB38U?tag=thenewyorktim-20"}]},{"age_group":"","amazon_product_url":"http:\/\/www.amazon.com\/Big-Little-Lies-Liane-Moriarty-ebook\/dp\/B00HDMMISA?tag=thenewyorktim-20","article_chapter_link":"","author":"Liane Moriarty","book_image":"https:\/\/s1.nyt.com\/du\/books\/images\/9780698138636.jpg","book_image_width":128,"book_image_height":193,"book_review_link":"https:\/\/www.nytimes.com\/2014\/07\/25\/books\/in-big-little-lies-liane-moriarty-finds-new-complications.html","contributor":"by Liane Moriarty","contributor_note":"","created_date":"2017-04-27 16:00:11","description":"Who will end up dead, and how, when three mothers with children in the same school become friends?","first_chapter_link":"","price":0,"primary_isbn10":"0698138635","primary_isbn13":"9780698138636","publisher":"Berkley","rank":4,"rank_last_week":2,"sunday_review_link":"","title":"BIG LITTLE LIES","updated_date":"2017-04-27 21:00:13","weeks_on_list":36,"buy_links":[{"name":"Local Booksellers","url":"http:\/\/www.indiebound.org\/book\/9780698138636?aff=NYT"},{"name":"Barnes and Noble","url":"http:\/\/www.anrdoezrs.net\/click-7990613-11819508?url=http%3A%2F%2Fwww.barnesandnoble.com%2Fw%2F%3Fean%3D9780698138636"},{"name":"Amazon","url":"http:\/\/www.amazon.com\/Big-Little-Lies-Liane-Moriarty-ebook\/dp\/B00HDMMISA?tag=thenewyorktim-20"}]},{"age_group":"","amazon_product_url":"http:\/\/www.amazon.com\/Man-Called-Ove-Novel\/dp\/1476738025?tag=thenewyorktim-20","article_chapter_link":"","author":"Fredrik Backman","book_image":"https:\/\/s1.nyt.com\/du\/books\/images\/9781476738024.jpg","book_image_width":318,"book_image_height":495,"book_review_link":"","contributor":"by Fredrik Backman","contributor_note":"","created_date":"2017-04-27 16:00:11","description":"A curmudgeon's gruff exterior masks a generosity of spirit. Originally published in Sweden in 2014.","first_chapter_link":"","price":0,"primary_isbn10":"1476738025","primary_isbn13":"9781476738024","publisher":"Washington Square","rank":5,"rank_last_week":8,"sunday_review_link":"","title":"A MAN CALLED OVE","updated_date":"2017-04-27 21:00:13","weeks_on_list":48,"buy_links":[{"name":"Local Booksellers","url":"http:\/\/www.indiebound.org\/book\/9781476738024?aff=NYT"},{"name":"Barnes and Noble","url":"http:\/\/www.anrdoezrs.net\/click-7990613-11819508?url=http%3A%2F%2Fwww.barnesandnoble.com%2Fw%2F%3Fean%3D9781476738024"},{"name":"Amazon","url":"http:\/\/www.amazon.com\/Man-Called-Ove-Novel\/dp\/1476738025?tag=thenewyorktim-20"}]}]},{"list_id":708,"list_name":"Combined Print and E-Book Nonfiction","list_name_encoded":"combined-print-and-e-book-nonfiction","display_name":"Combined Print & E-Book Nonfiction","updated":"WEEKLY","list_image":"https:\/\/s1.nyt.com\/du\/books\/images\/9780553447095.jpg","list_image_width":326,"list_image_height":495,"books":[{"age_group":"","amazon_product_url":"https:\/\/www.amazon.com\/Shattered-Inside-Hillary-Clintons-Campaign-ebook\/dp\/B01JWDWP6W?tag=thenewyorktim-20","article_chapter_link":"","author":"Jonathan Allen and Amie Parnes","book_image":"https:\/\/s1.nyt.com\/du\/books\/images\/9780553447095.jpg","book_image_width":326,"book_image_height":495,"book_review_link":"","contributor":"by Jonathan Allen and Amie Parnes","contributor_note":"","created_date":"2017-04-27 16:00:12","description":"An examination of Hillary Clinton\u2019s presidential campaign.","first_chapter_link":"","price":0,"primary_isbn10":"0553447092","primary_isbn13":"9780553447095","publisher":"Crown","rank":1,"rank_last_week":0,"sunday_review_link":"","title":"SHATTERED","updated_date":"2017-04-27 21:00:14","weeks_on_list":1,"buy_links":[{"name":"Local Booksellers","url":"http:\/\/www.indiebound.org\/book\/9780553447095?aff=NYT"},{"name":"Barnes and Noble","url":"http:\/\/www.anrdoezrs.net\/click-7990613-11819508?url=http%3A%2F%2Fwww.barnesandnoble.com%2Fw%2F%3Fean%3D9780553447095"},{"name":"Amazon","url":"https:\/\/www.amazon.com\/Shattered-Inside-Hillary-Clintons-Campaign-ebook\/dp\/B01JWDWP6W?tag=thenewyorktim-20"}]},{"age_group":"","amazon_product_url":"https:\/\/www.amazon.com\/This-Fight-Our-Battle-Americas\/dp\/1250120616?tag=thenewyorktim-20","article_chapter_link":"","author":"Elizabeth Warren","book_image":"https:\/\/s1.nyt.com\/du\/books\/images\/9781250120618.jpg","book_image_width":327,"book_image_height":495,"book_review_link":"https:\/\/www.nytimes.com\/2017\/04\/18\/books\/review\/this-fight-is-our-fight-elizabeth-warren.html","contributor":"by Elizabeth Warren","contributor_note":"","created_date":"2017-04-27 16:00:12","description":"The Massachusetts senator offers a program for Democratic resistance to President Trump.","first_chapter_link":"","price":0,"primary_isbn10":"1250120616","primary_isbn13":"9781250120618","publisher":"Metropolitan\/Holt","rank":2,"rank_last_week":0,"sunday_review_link":"","title":"THIS FIGHT IS OUR FIGHT","updated_date":"2017-04-27 21:00:14","weeks_on_list":1,"buy_links":[{"name":"Local Booksellers","url":"http:\/\/www.indiebound.org\/book\/9781250120618?aff=NYT"},{"name":"Barnes and Noble","url":"http:\/\/www.anrdoezrs.net\/click-7990613-11819508?url=http%3A%2F%2Fwww.barnesandnoble.com%2Fw%2F%3Fean%3D9781250120618"},{"name":"Amazon","url":"https:\/\/www.amazon.com\/This-Fight-Our-Battle-Americas\/dp\/1250120616?tag=thenewyorktim-20"}]},{"age_group":"","amazon_product_url":"https:\/\/www.amazon.com\/Killers-Flower-Moon-Osage-Murders\/dp\/0385534248?tag=thenewyorktim-20","article_chapter_link":"","author":"David Grann","book_image":"https:\/\/s1.nyt.com\/du\/books\/images\/9780385534246.jpg","book_image_width":326,"book_image_height":495,"book_review_link":"https:\/\/www.nytimes.com\/2017\/04\/28\/books\/review\/killers-of-the-flower-moon-david-grann.html","contributor":"by David Grann","contributor_note":"","created_date":"2017-04-27 16:00:12","description":"The story of a murder spree in 1920s Oklahoma that targeted Osage Indians, whose lands contained oil.","first_chapter_link":"","price":0,"primary_isbn10":"0385534248","primary_isbn13":"9780385534246","publisher":"Doubleday","rank":3,"rank_last_week":0,"sunday_review_link":"","title":"KILLERS OF THE FLOWER MOON","updated_date":"2017-04-27 21:00:14","weeks_on_list":1,"buy_links":[{"name":"Local Booksellers","url":"http:\/\/www.indiebound.org\/book\/9780385534246?aff=NYT"},{"name":"Barnes and Noble","url":"http:\/\/www.anrdoezrs.net\/click-7990613-11819508?url=http%3A%2F%2Fwww.barnesandnoble.com%2Fw%2F%3Fean%3D9780385534246"},{"name":"Amazon","url":"https:\/\/www.amazon.com\/Killers-Flower-Moon-Osage-Murders\/dp\/0385534248?tag=thenewyorktim-20"}]},{"age_group":"","amazon_product_url":"http:\/\/www.amazon.com\/The-Zookeepers-Wife-War-Story\/dp\/039333306X?tag=thenewyorktim-20","article_chapter_link":"","author":"Diane Ackerman","book_image":"https:\/\/s1.nyt.com\/du\/books\/images\/9780393333060.jpg","book_image_width":300,"book_image_height":450,"book_review_link":"","contributor":"by Diane Ackerman","contributor_note":"","created_date":"2017-04-27 16:00:12","description":"How a Warsaw couple sheltered Jews and members of the Resistance during World War II. Originally published in 2007; now the basis of a movie,","first_chapter_link":"","price":0,"primary_isbn10":"039333306X","primary_isbn13":"9780393333060","publisher":"Norton","rank":4,"rank_last_week":2,"sunday_review_link":"https:\/\/www.nytimes.com\/2007\/09\/09\/books\/review\/Max-t.html","title":"THE ZOOKEEPER'S WIFE","updated_date":"2017-04-27 21:00:14","weeks_on_list":11,"buy_links":[{"name":"Local Booksellers","url":"http:\/\/www.indiebound.org\/book\/9780393333060?aff=NYT"},{"name":"Barnes and Noble","url":"http:\/\/www.anrdoezrs.net\/click-7990613-11819508?url=http%3A%2F%2Fwww.barnesandnoble.com%2Fw%2F%3Fean%3D9780393333060"},{"name":"Amazon","url":"http:\/\/www.amazon.com\/The-Zookeepers-Wife-War-Story\/dp\/039333306X?tag=thenewyorktim-20"}]},{"age_group":"","amazon_product_url":"https:\/\/www.amazon.com\/Old-School-Life-Sane-Lane\/dp\/1250135796?tag=thenewyorktim-20","article_chapter_link":"","author":"Bill O'Reilly and Bruce Feirstein","book_image":"https:\/\/s1.nyt.com\/du\/books\/images\/9781250135797.jpg","book_image_width":328,"book_image_height":495,"book_review_link":"","contributor":"by Bill O'Reilly and Bruce Feirstein","contributor_note":"","created_date":"2017-04-27 16:00:12","description":"A defense of \u201cold school\u201d traditional values versus \u201csnowflakes.\"","first_chapter_link":"","price":0,"primary_isbn10":"1250135796","primary_isbn13":"9781250135797","publisher":"Holt","rank":5,"rank_last_week":1,"sunday_review_link":"","title":"OLD SCHOOL","updated_date":"2017-04-27 21:00:14","weeks_on_list":4,"buy_links":[{"name":"Local Booksellers","url":"http:\/\/www.indiebound.org\/book\/9781250135797?aff=NYT"},{"name":"Barnes and Noble","url":"http:\/\/www.anrdoezrs.net\/click-7990613-11819508?url=http%3A%2F%2Fwww.barnesandnoble.com%2Fw%2F%3Fean%3D9781250135797"},{"name":"Amazon","url":"https:\/\/www.amazon.com\/Old-School-Life-Sane-Lane\/dp\/1250135796?tag=thenewyorktim-20"}]}]},{"list_id":1,"list_name":"Hardcover Fiction","list_name_encoded":"hardcover-fiction","display_name":"Hardcover Fiction","updated":"WEEKLY","list_image":"https:\/\/s1.nyt.com\/du\/books\/images\/9781455586561.jpg","list_image_width":330,"list_image_height":480,"books":[{"age_group":"","amazon_product_url":"https:\/\/www.amazon.com\/Fix-Amos-Decker-David-Baldacci\/dp\/1455586560?tag=thenewyorktim-20","article_chapter_link":"","author":"David Baldacci","book_image":"https:\/\/s1.nyt.com\/du\/books\/images\/9781455586561.jpg","book_image_width":330,"book_image_height":480,"book_review_link":"","contributor":"by David Baldacci","contributor_note":"","created_date":"2017-04-27 16:00:03","description":"The detective Amos Decker (\u201cMemory Man\u201d) witnesses a murder-suicide that turns out to be a matter of national security.","first_chapter_link":"","price":0,"primary_isbn10":"1455586560","primary_isbn13":"9781455586561","publisher":"Grand Central","rank":1,"rank_last_week":0,"sunday_review_link":"","title":"THE FIX","updated_date":"2017-04-27 21:00:03","weeks_on_list":1,"buy_links":[{"name":"Local Booksellers","url":"http:\/\/www.indiebound.org\/book\/9781455586561?aff=NYT"},{"name":"Barnes and Noble","url":"http:\/\/www.anrdoezrs.net\/click-7990613-11819508?url=http%3A%2F%2Fwww.barnesandnoble.com%2Fw%2F%3Fean%3D9781455586561"},{"name":"Amazon","url":"https:\/\/www.amazon.com\/Fix-Amos-Decker-David-Baldacci\/dp\/1455586560?tag=thenewyorktim-20"}]},{"age_group":"","amazon_product_url":"https:\/\/www.amazon.com\/Black-Book-James-Patterson-ebook\/dp\/B01HZFB38U?tag=thenewyorktim-20","article_chapter_link":"","author":"James Patterson and David Ellis","book_image":"https:\/\/s1.nyt.com\/du\/books\/images\/9780316464147.jpg","book_image_width":321,"book_image_height":495,"book_review_link":"","contributor":"by James Patterson and David Ellis","contributor_note":"","created_date":"2017-04-27 16:00:03","description":"After a raid on a brothel that serviced Chicago\u2019s elite, the madam\u2019s black book has disappeared.","first_chapter_link":"","price":0,"primary_isbn10":"0316273880","primary_isbn13":"9780316273886","publisher":"Little, Brown","rank":2,"rank_last_week":1,"sunday_review_link":"","title":"THE BLACK BOOK","updated_date":"2017-04-27 21:00:03","weeks_on_list":4,"buy_links":[{"name":"Local Booksellers","url":"http:\/\/www.indiebound.org\/book\/9780316273886?aff=NYT"},{"name":"Barnes and Noble","url":"http:\/\/www.anrdoezrs.net\/click-7990613-11819508?url=http%3A%2F%2Fwww.barnesandnoble.com%2Fw%2F%3Fean%3D9780316273886"},{"name":"Amazon","url":"https:\/\/www.amazon.com\/Black-Book-James-Patterson-ebook\/dp\/B01HZFB38U?tag=thenewyorktim-20"}]},{"age_group":"","amazon_product_url":"https:\/\/www.amazon.com\/Fast-Loose-Stone-Barrington-Novel-ebook\/dp\/B01J2STXC6?tag=thenewyorktim-20","article_chapter_link":"","author":"Stuart Woods","book_image":"https:\/\/s1.nyt.com\/du\/books\/images\/9780399574214.jpg","book_image_width":328,"book_image_height":495,"book_review_link":"","contributor":"by Stuart Woods","contributor_note":"","created_date":"2017-04-27 16:00:03","description":"In the 41st Stone Barrington novel, the New York attorney acquires a ruthless, hot-headed enemy.","first_chapter_link":"","price":0,"primary_isbn10":"0399574190","primary_isbn13":"9780399574191","publisher":"Putnam","rank":3,"rank_last_week":0,"sunday_review_link":"","title":"FAST AND LOOSE","updated_date":"2017-04-27 21:00:04","weeks_on_list":1,"buy_links":[{"name":"Local Booksellers","url":"http:\/\/www.indiebound.org\/book\/9780399574191?aff=NYT"},{"name":"Barnes and Noble","url":"http:\/\/www.anrdoezrs.net\/click-7990613-11819508?url=http%3A%2F%2Fwww.barnesandnoble.com%2Fw%2F%3Fean%3D9780399574191"},{"name":"Amazon","url":"https:\/\/www.amazon.com\/Fast-Loose-Stone-Barrington-Novel-ebook\/dp\/B01J2STXC6?tag=thenewyorktim-20"}]},{"age_group":"","amazon_product_url":"https:\/\/www.amazon.com\/Thrawn-Star-Wars-Timothy-Zahn\/dp\/0345511271?tag=thenewyorktim-20","article_chapter_link":"","author":"Timothy Zahn","book_image":"https:\/\/s1.nyt.com\/du\/books\/images\/9780345511270.jpg","book_image_width":326,"book_image_height":495,"book_review_link":"","contributor":"by Timothy Zahn","contributor_note":"","created_date":"2017-04-27 16:00:03","description":"The origins of Grand Admiral Thrawn, an iconic \u201cStar Wars\u201d villain.","first_chapter_link":"","price":0,"primary_isbn10":"0345511271","primary_isbn13":"9780345511270","publisher":"Del Rey","rank":4,"rank_last_week":2,"sunday_review_link":"","title":"THRAWN","updated_date":"2017-04-27 21:00:04","weeks_on_list":2,"buy_links":[{"name":"Local Booksellers","url":"http:\/\/www.indiebound.org\/book\/9780345511270?aff=NYT"},{"name":"Barnes and Noble","url":"http:\/\/www.anrdoezrs.net\/click-7990613-11819508?url=http%3A%2F%2Fwww.barnesandnoble.com%2Fw%2F%3Fean%3D9780345511270"},{"name":"Amazon","url":"https:\/\/www.amazon.com\/Thrawn-Star-Wars-Timothy-Zahn\/dp\/0345511271?tag=thenewyorktim-20"}]},{"age_group":"","amazon_product_url":"https:\/\/www.amazon.com\/Myself-Alone-Mary-Higgins-Clark-ebook\/dp\/B01HMXRYWY?tag=thenewyorktim-20","article_chapter_link":"","author":"Mary Higgins Clark","book_image":"https:\/\/s1.nyt.com\/du\/books\/images\/9781501131134.jpg","book_image_width":328,"book_image_height":495,"book_review_link":"","contributor":"by Mary Higgins Clark","contributor_note":"","created_date":"2017-04-27 16:00:03","description":"On a luxury cruise ship, a wealthy aristocrat is found murdered, and her emerald necklace is gone.","first_chapter_link":"","price":0,"primary_isbn10":"1501131117","primary_isbn13":"9781501131110","publisher":"Simon & Schuster","rank":5,"rank_last_week":3,"sunday_review_link":"","title":"ALL BY MYSELF, ALONE","updated_date":"2017-04-27 21:00:04","weeks_on_list":3,"buy_links":[{"name":"Local Booksellers","url":"http:\/\/www.indiebound.org\/book\/9781501131110?aff=NYT"},{"name":"Barnes and Noble","url":"http:\/\/www.anrdoezrs.net\/click-7990613-11819508?url=http%3A%2F%2Fwww.barnesandnoble.com%2Fw%2F%3Fean%3D9781501131110"},{"name":"Amazon","url":"https:\/\/www.amazon.com\/Myself-Alone-Mary-Higgins-Clark-ebook\/dp\/B01HMXRYWY?tag=thenewyorktim-20"}]}]},{"list_id":2,"list_name":"Hardcover Nonfiction","list_name_encoded":"hardcover-nonfiction","display_name":"Hardcover Nonfiction","updated":"WEEKLY","list_image":"https:\/\/s1.nyt.com\/du\/books\/images\/9781250120618.jpg","list_image_width":327,"list_image_height":495,"books":[{"age_group":"","amazon_product_url":"https:\/\/www.amazon.com\/This-Fight-Our-Battle-Americas\/dp\/1250120616?tag=thenewyorktim-20","article_chapter_link":"","author":"Elizabeth Warren","book_image":"https:\/\/s1.nyt.com\/du\/books\/images\/9781250120618.jpg","book_image_width":327,"book_image_height":495,"book_review_link":"https:\/\/www.nytimes.com\/2017\/04\/18\/books\/review\/this-fight-is-our-fight-elizabeth-warren.html","contributor":"by Elizabeth Warren","contributor_note":"","created_date":"2017-04-27 16:00:08","description":"The Massachusetts senator calls for restored financial regulation, stronger social programs, and renewed investment in education, research and infrastructure.","first_chapter_link":"","price":0,"primary_isbn10":"1250120616","primary_isbn13":"9781250120618","publisher":"Metropolitan\/Holt","rank":1,"rank_last_week":0,"sunday_review_link":"","title":"THIS FIGHT IS OUR FIGHT","updated_date":"2017-04-27 21:00:10","weeks_on_list":1,"buy_links":[{"name":"Local Booksellers","url":"http:\/\/www.indiebound.org\/book\/9781250120618?aff=NYT"},{"name":"Barnes and Noble","url":"http:\/\/www.anrdoezrs.net\/click-7990613-11819508?url=http%3A%2F%2Fwww.barnesandnoble.com%2Fw%2F%3Fean%3D9781250120618"},{"name":"Amazon","url":"https:\/\/www.amazon.com\/This-Fight-Our-Battle-Americas\/dp\/1250120616?tag=thenewyorktim-20"}]},{"age_group":"","amazon_product_url":"https:\/\/www.amazon.com\/Shattered-Inside-Hillary-Clintons-Campaign-ebook\/dp\/B01JWDWP6W?tag=thenewyorktim-20","article_chapter_link":"","author":"Jonathan Allen and Amie Parnes","book_image":"https:\/\/s1.nyt.com\/du\/books\/images\/9780553447095.jpg","book_image_width":326,"book_image_height":495,"book_review_link":"","contributor":"by Jonathan Allen and Amie Parnes","contributor_note":"","created_date":"2017-04-27 16:00:08","description":"An examination of Hillary Clinton\u2019s presidential campaign.","first_chapter_link":"","price":0,"primary_isbn10":"0553447084","primary_isbn13":"9780553447088","publisher":"Crown","rank":2,"rank_last_week":0,"sunday_review_link":"","title":"SHATTERED","updated_date":"2017-04-27 21:00:10","weeks_on_list":1,"buy_links":[{"name":"Local Booksellers","url":"http:\/\/www.indiebound.org\/book\/9780553447088?aff=NYT"},{"name":"Barnes and Noble","url":"http:\/\/www.anrdoezrs.net\/click-7990613-11819508?url=http%3A%2F%2Fwww.barnesandnoble.com%2Fw%2F%3Fean%3D9780553447088"},{"name":"Amazon","url":"https:\/\/www.amazon.com\/Shattered-Inside-Hillary-Clintons-Campaign-ebook\/dp\/B01JWDWP6W?tag=thenewyorktim-20"}]},{"age_group":"","amazon_product_url":"https:\/\/www.amazon.com\/Note-Self-Connor-Franta\/dp\/1501158015?tag=thenewyorktim-20","article_chapter_link":"","author":"Connor Franta","book_image":"https:\/\/s1.nyt.com\/du\/books\/images\/9781501158018.jpg","book_image_width":330,"book_image_height":493,"book_review_link":"","contributor":"by Connor Franta","contributor_note":"","created_date":"2017-04-27 16:00:08","description":"The internet personality discloses his struggles with depression and other issues in short essays and diary-like entries.","first_chapter_link":"","price":0,"primary_isbn10":"1501158015","primary_isbn13":"9781501158018","publisher":"Atria\/Keywords","rank":3,"rank_last_week":0,"sunday_review_link":"","title":"NOTE TO SELF","updated_date":"2017-04-27 21:00:10","weeks_on_list":1,"buy_links":[{"name":"Local Booksellers","url":"http:\/\/www.indiebound.org\/book\/9781501158018?aff=NYT"},{"name":"Barnes and Noble","url":"http:\/\/www.anrdoezrs.net\/click-7990613-11819508?url=http%3A%2F%2Fwww.barnesandnoble.com%2Fw%2F%3Fean%3D9781501158018"},{"name":"Amazon","url":"https:\/\/www.amazon.com\/Note-Self-Connor-Franta\/dp\/1501158015?tag=thenewyorktim-20"}]},{"age_group":"","amazon_product_url":"https:\/\/www.amazon.com\/Old-School-Life-Sane-Lane\/dp\/1250135796?tag=thenewyorktim-20","article_chapter_link":"","author":"Bill O'Reilly and Bruce Feirstein","book_image":"https:\/\/s1.nyt.com\/du\/books\/images\/9781250135797.jpg","book_image_width":328,"book_image_height":495,"book_review_link":"","contributor":"by Bill O'Reilly and Bruce Feirstein","contributor_note":"","created_date":"2017-04-27 16:00:08","description":"A defense of \u201cold school\u201d traditional values versus \u201csnowflakes.\u201d","first_chapter_link":"","price":0,"primary_isbn10":"1250135796","primary_isbn13":"9781250135797","publisher":"Holt","rank":4,"rank_last_week":1,"sunday_review_link":"","title":"OLD SCHOOL","updated_date":"2017-04-27 21:00:10","weeks_on_list":4,"buy_links":[{"name":"Local Booksellers","url":"http:\/\/www.indiebound.org\/book\/9781250135797?aff=NYT"},{"name":"Barnes and Noble","url":"http:\/\/www.anrdoezrs.net\/click-7990613-11819508?url=http%3A%2F%2Fwww.barnesandnoble.com%2Fw%2F%3Fean%3D9781250135797"},{"name":"Amazon","url":"https:\/\/www.amazon.com\/Old-School-Life-Sane-Lane\/dp\/1250135796?tag=thenewyorktim-20"}]},{"age_group":"","amazon_product_url":"https:\/\/www.amazon.com\/Killers-Flower-Moon-Osage-Murders\/dp\/0385534248?tag=thenewyorktim-20","article_chapter_link":"","author":"David Grann","book_image":"https:\/\/s1.nyt.com\/du\/books\/images\/9780385534246.jpg","book_image_width":326,"book_image_height":495,"book_review_link":"https:\/\/www.nytimes.com\/2017\/04\/28\/books\/review\/killers-of-the-flower-moon-david-grann.html","contributor":"by David Grann","contributor_note":"","created_date":"2017-04-27 16:00:08","description":"The story of a murder spree in 1920s Oklahoma that targeted Osage Indians, whose lands contained oil. The fledgling F.B.I. intervened, ineffectively.","first_chapter_link":"","price":0,"primary_isbn10":"0385534248","primary_isbn13":"9780385534246","publisher":"Doubleday","rank":5,"rank_last_week":0,"sunday_review_link":"","title":"KILLERS OF THE FLOWER MOON","updated_date":"2017-04-27 21:00:10","weeks_on_list":1,"buy_links":[{"name":"Local Booksellers","url":"http:\/\/www.indiebound.org\/book\/9780385534246?aff=NYT"},{"name":"Barnes and Noble","url":"http:\/\/www.anrdoezrs.net\/click-7990613-11819508?url=http%3A%2F%2Fwww.barnesandnoble.com%2Fw%2F%3Fean%3D9780385534246"},{"name":"Amazon","url":"https:\/\/www.amazon.com\/Killers-Flower-Moon-Osage-Murders\/dp\/0385534248?tag=thenewyorktim-20"}]}]},{"list_id":17,"list_name":"Trade Fiction Paperback","list_name_encoded":"trade-fiction-paperback","display_name":"Paperback Trade Fiction","updated":"WEEKLY","list_image":"https:\/\/s1.nyt.com\/du\/books\/images\/9781449474256.jpg","list_image_width":319,"list_image_height":495,"books":[{"age_group":"","amazon_product_url":"http:\/\/www.amazon.com\/Milk-Honey-Rupi-Kaur\/dp\/144947425X?tag=thenewyorktim-20","article_chapter_link":"","author":"Rupi Kaur","book_image":"https:\/\/s1.nyt.com\/du\/books\/images\/9781449474256.jpg","book_image_width":319,"book_image_height":495,"book_review_link":"","contributor":"by Rupi Kaur","contributor_note":"","created_date":"2017-04-27 16:00:08","description":"","first_chapter_link":"","price":0,"primary_isbn10":"144947425X","primary_isbn13":"9781449474256","publisher":"Andrews McMeel","rank":1,"rank_last_week":1,"sunday_review_link":"","title":"MILK AND HONEY","updated_date":"2017-04-27 21:00:09","weeks_on_list":54,"buy_links":[{"name":"Local Booksellers","url":"http:\/\/www.indiebound.org\/book\/9781449474256?aff=NYT"},{"name":"Barnes and Noble","url":"http:\/\/www.anrdoezrs.net\/click-7990613-11819508?url=http%3A%2F%2Fwww.barnesandnoble.com%2Fw%2F%3Fean%3D9781449474256"},{"name":"Amazon","url":"http:\/\/www.amazon.com\/Milk-Honey-Rupi-Kaur\/dp\/144947425X?tag=thenewyorktim-20"}]},{"age_group":"","amazon_product_url":"http:\/\/www.amazon.com\/Woman-Cabin-10-Ruth-Ware-ebook\/dp\/B019DKO5BM?tag=thenewyorktim-20","article_chapter_link":"","author":"Ruth Ware","book_image":"https:\/\/s1.nyt.com\/du\/books\/images\/9781501132940.jpg","book_image_width":330,"book_image_height":495,"book_review_link":"","contributor":"by Ruth Ware","contributor_note":"","created_date":"2017-04-27 16:00:08","description":"","first_chapter_link":"","price":0,"primary_isbn10":"1501132954","primary_isbn13":"9781501132957","publisher":"Scout","rank":2,"rank_last_week":2,"sunday_review_link":"","title":"THE WOMAN IN CABIN 10","updated_date":"2017-04-27 21:00:09","weeks_on_list":2,"buy_links":[{"name":"Local Booksellers","url":"http:\/\/www.indiebound.org\/book\/9781501132957?aff=NYT"},{"name":"Barnes and Noble","url":"http:\/\/www.anrdoezrs.net\/click-7990613-11819508?url=http%3A%2F%2Fwww.barnesandnoble.com%2Fw%2F%3Fean%3D9781501132957"},{"name":"Amazon","url":"http:\/\/www.amazon.com\/Woman-Cabin-10-Ruth-Ware-ebook\/dp\/B019DKO5BM?tag=thenewyorktim-20"}]},{"age_group":"","amazon_product_url":"http:\/\/www.amazon.com\/All-Light-We-Cannot-See\/dp\/1476746583?tag=thenewyorktim-20","article_chapter_link":"","author":"Anthony Doerr","book_image":"https:\/\/s1.nyt.com\/du\/books\/images\/9781476746586.jpg","book_image_width":128,"book_image_height":192,"book_review_link":"","contributor":"by Anthony Doerr","contributor_note":"","created_date":"2017-04-27 16:00:08","description":"","first_chapter_link":"","price":0,"primary_isbn10":"1501173219","primary_isbn13":"9781501173219","publisher":"Scribner","rank":3,"rank_last_week":3,"sunday_review_link":"https:\/\/www.nytimes.com\/2014\/05\/11\/books\/review\/all-the-light-we-cannot-see-by-anthony-doerr.html","title":"ALL THE LIGHT WE CANNOT SEE","updated_date":"2017-04-27 21:00:09","weeks_on_list":3,"buy_links":[{"name":"Local Booksellers","url":"http:\/\/www.indiebound.org\/book\/9781501173219?aff=NYT"},{"name":"Barnes and Noble","url":"http:\/\/www.anrdoezrs.net\/click-7990613-11819508?url=http%3A%2F%2Fwww.barnesandnoble.com%2Fw%2F%3Fean%3D9781501173219"},{"name":"Amazon","url":"http:\/\/www.amazon.com\/All-Light-We-Cannot-See\/dp\/1476746583?tag=thenewyorktim-20"}]},{"age_group":"","amazon_product_url":"https:\/\/www.amazon.com\/Handmaids-Tale-Margaret-Atwood-ebook\/dp\/B003JFJHTS?tag=thenewyorktim-20","article_chapter_link":"","author":"Margaret Atwood","book_image":"https:\/\/s1.nyt.com\/du\/books\/images\/9780547345666.jpg","book_image_width":330,"book_image_height":485,"book_review_link":"","contributor":"by Margaret Atwood","contributor_note":"","created_date":"2017-04-27 16:00:08","description":"","first_chapter_link":"","price":0,"primary_isbn10":"038549081X","primary_isbn13":"9780385490818","publisher":"Anchor","rank":4,"rank_last_week":10,"sunday_review_link":"https:\/\/www.nytimes.com\/1986\/02\/09\/books\/no-headline-423986.html","title":"THE HANDMAID'S TALE","updated_date":"2017-04-27 21:00:09","weeks_on_list":11,"buy_links":[{"name":"Local Booksellers","url":"http:\/\/www.indiebound.org\/book\/9780385490818?aff=NYT"},{"name":"Barnes and Noble","url":"http:\/\/www.anrdoezrs.net\/click-7990613-11819508?url=http%3A%2F%2Fwww.barnesandnoble.com%2Fw%2F%3Fean%3D9780385490818"},{"name":"Amazon","url":"https:\/\/www.amazon.com\/Handmaids-Tale-Margaret-Atwood-ebook\/dp\/B003JFJHTS?tag=thenewyorktim-20"}]},{"age_group":"","amazon_product_url":"http:\/\/www.amazon.com\/Man-Called-Ove-Novel\/dp\/1476738025?tag=thenewyorktim-20","article_chapter_link":"","author":"Fredrik Backman","book_image":"https:\/\/s1.nyt.com\/du\/books\/images\/9781476738024.jpg","book_image_width":318,"book_image_height":495,"book_review_link":"","contributor":"by Fredrik Backman","contributor_note":"","created_date":"2017-04-27 16:00:08","description":"","first_chapter_link":"","price":0,"primary_isbn10":"1476738025","primary_isbn13":"9781476738024","publisher":"Washington Square","rank":5,"rank_last_week":5,"sunday_review_link":"","title":"A MAN CALLED OVE","updated_date":"2017-04-27 21:00:09","weeks_on_list":69,"buy_links":[{"name":"Local Booksellers","url":"http:\/\/www.indiebound.org\/book\/9781476738024?aff=NYT"},{"name":"Barnes and Noble","url":"http:\/\/www.anrdoezrs.net\/click-7990613-11819508?url=http%3A%2F%2Fwww.barnesandnoble.com%2Fw%2F%3Fean%3D9781476738024"},{"name":"Amazon","url":"http:\/\/www.amazon.com\/Man-Called-Ove-Novel\/dp\/1476738025?tag=thenewyorktim-20"}]}]},{"list_id":4,"list_name":"Paperback Nonfiction","list_name_encoded":"paperback-nonfiction","display_name":"Paperback Nonfiction","updated":"WEEKLY","list_image":"https:\/\/s1.nyt.com\/du\/books\/images\/9780393333060.jpg","list_image_width":300,"list_image_height":450,"books":[{"age_group":"","amazon_product_url":"http:\/\/www.amazon.com\/The-Zookeepers-Wife-War-Story\/dp\/039333306X?tag=thenewyorktim-20","article_chapter_link":"","author":"Diane Ackerman","book_image":"https:\/\/s1.nyt.com\/du\/books\/images\/9780393333060.jpg","book_image_width":300,"book_image_height":450,"book_review_link":"","contributor":"by Diane Ackerman","contributor_note":"","created_date":"2017-04-27 16:00:09","description":"","first_chapter_link":"","price":0,"primary_isbn10":"039333306X","primary_isbn13":"9780393333060","publisher":"Norton","rank":1,"rank_last_week":1,"sunday_review_link":"https:\/\/www.nytimes.com\/2007\/09\/09\/books\/review\/Max-t.html","title":"THE ZOOKEEPER'S WIFE","updated_date":"2017-04-27 21:00:12","weeks_on_list":38,"buy_links":[{"name":"Local Booksellers","url":"http:\/\/www.indiebound.org\/book\/9780393333060?aff=NYT"},{"name":"Barnes and Noble","url":"http:\/\/www.anrdoezrs.net\/click-7990613-11819508?url=http%3A%2F%2Fwww.barnesandnoble.com%2Fw%2F%3Fean%3D9780393333060"},{"name":"Amazon","url":"http:\/\/www.amazon.com\/The-Zookeepers-Wife-War-Story\/dp\/039333306X?tag=thenewyorktim-20"}]},{"age_group":"","amazon_product_url":"http:\/\/www.amazon.com\/The-Immortal-Life-Henrietta-Lacks\/dp\/1400052181?tag=thenewyorktim-20","article_chapter_link":"https:\/\/www.nytimes.com\/2010\/02\/02\/health\/02seco.html","author":"Rebecca Skloot","book_image":"https:\/\/s1.nyt.com\/du\/books\/images\/9781400052189.jpg","book_image_width":182,"book_image_height":280,"book_review_link":"https:\/\/www.nytimes.com\/2010\/02\/03\/books\/03book.html","contributor":"by Rebecca Skloot","contributor_note":"","created_date":"2017-04-27 16:00:09","description":"","first_chapter_link":"https:\/\/www.nytimes.com\/2010\/03\/03\/books\/excerpt-immortal-life-of-henrietta-lacks.html","price":0,"primary_isbn10":"1400052181","primary_isbn13":"9781400052189","publisher":"Broadway","rank":2,"rank_last_week":3,"sunday_review_link":"https:\/\/www.nytimes.com\/2010\/02\/07\/books\/review\/Margonelli-t.html","title":"THE IMMORTAL LIFE OF HENRIETTA LACKS","updated_date":"2017-04-27 21:00:12","weeks_on_list":189,"buy_links":[{"name":"Local Booksellers","url":"http:\/\/www.indiebound.org\/book\/9781400052189?aff=NYT"},{"name":"Barnes and Noble","url":"http:\/\/www.anrdoezrs.net\/click-7990613-11819508?url=http%3A%2F%2Fwww.barnesandnoble.com%2Fw%2F%3Fean%3D9781400052189"},{"name":"Amazon","url":"http:\/\/www.amazon.com\/The-Immortal-Life-Henrietta-Lacks\/dp\/1400052181?tag=thenewyorktim-20"}]},{"age_group":"","amazon_product_url":"http:\/\/www.amazon.com\/Hidden-Figures-American-Untold-Mathematicians-ebook\/dp\/B0166JFFD0?tag=thenewyorktim-20","article_chapter_link":"","author":"Margot Lee Shetterly","book_image":"https:\/\/s1.nyt.com\/du\/books\/images\/9780062363619.jpg","book_image_width":330,"book_image_height":494,"book_review_link":"","contributor":"by Margot Lee Shetterly","contributor_note":"","created_date":"2017-04-27 16:00:09","description":"","first_chapter_link":"","price":0,"primary_isbn10":"0062363603","primary_isbn13":"9780062363602","publisher":"Morrow\/HarperCollins","rank":3,"rank_last_week":2,"sunday_review_link":"","title":"HIDDEN FIGURES","updated_date":"2017-04-27 21:00:12","weeks_on_list":20,"buy_links":[{"name":"Local Booksellers","url":"http:\/\/www.indiebound.org\/book\/9780062363602?aff=NYT"},{"name":"Barnes and Noble","url":"http:\/\/www.anrdoezrs.net\/click-7990613-11819508?url=http%3A%2F%2Fwww.barnesandnoble.com%2Fw%2F%3Fean%3D9780062363602"},{"name":"Amazon","url":"http:\/\/www.amazon.com\/Hidden-Figures-American-Untold-Mathematicians-ebook\/dp\/B0166JFFD0?tag=thenewyorktim-20"}]},{"age_group":"","amazon_product_url":"http:\/\/www.amazon.com\/The-Third-Wave-Entrepreneurs-Vision-ebook\/dp\/B010MH1ENW?tag=thenewyorktim-20","article_chapter_link":"","author":"Steve Case","book_image":"https:\/\/s1.nyt.com\/du\/books\/images\/9781501132605.jpg","book_image_width":323,"book_image_height":495,"book_review_link":"","contributor":"by Steve Case","contributor_note":"","created_date":"2017-04-27 16:00:09","description":"","first_chapter_link":"","price":0,"primary_isbn10":"1501132598","primary_isbn13":"9781501132599","publisher":"Simon & Schuster","rank":4,"rank_last_week":0,"sunday_review_link":"","title":"THE THIRD WAVE","updated_date":"2017-04-27 21:00:12","weeks_on_list":1,"buy_links":[{"name":"Local Booksellers","url":"http:\/\/www.indiebound.org\/book\/9781501132599?aff=NYT"},{"name":"Barnes and Noble","url":"http:\/\/www.anrdoezrs.net\/click-7990613-11819508?url=http%3A%2F%2Fwww.barnesandnoble.com%2Fw%2F%3Fean%3D9781501132599"},{"name":"Amazon","url":"http:\/\/www.amazon.com\/The-Third-Wave-Entrepreneurs-Vision-ebook\/dp\/B010MH1ENW?tag=thenewyorktim-20"}]},{"age_group":"","amazon_product_url":"http:\/\/www.amazon.com\/The-Lost-City-Deadly-Obsession\/dp\/1400078458?tag=thenewyorktim-20","article_chapter_link":"","author":"David Grann","book_image":"https:\/\/s1.nyt.com\/du\/books\/images\/9780385513531.jpg","book_image_width":315,"book_image_height":495,"book_review_link":"https:\/\/www.nytimes.com\/2009\/03\/17\/books\/17kaku.html?ref=books","contributor":"by David Grann","contributor_note":"","created_date":"2017-04-27 16:00:09","description":"","first_chapter_link":"","price":0,"primary_isbn10":"1400078458","primary_isbn13":"9781400078455","publisher":"Vintage Departures","rank":5,"rank_last_week":6,"sunday_review_link":"https:\/\/www.nytimes.com\/2009\/03\/01\/books\/review\/Cohen-t.html","title":"THE LOST CITY OF Z","updated_date":"2017-04-27 21:00:12","weeks_on_list":21,"buy_links":[{"name":"Local Booksellers","url":"http:\/\/www.indiebound.org\/book\/9781400078455?aff=NYT"},{"name":"Barnes and Noble","url":"http:\/\/www.anrdoezrs.net\/click-7990613-11819508?url=http%3A%2F%2Fwww.barnesandnoble.com%2Fw%2F%3Fean%3D9781400078455"},{"name":"Amazon","url":"http:\/\/www.amazon.com\/The-Lost-City-Deadly-Obsession\/dp\/1400078458?tag=thenewyorktim-20"}]}]},{"list_id":24,"list_name":"Advice How-To and Miscellaneous","list_name_encoded":"advice-how-to-and-miscellaneous","display_name":"Advice, How-To & Miscellaneous","updated":"WEEKLY","list_image":"https:\/\/s1.nyt.com\/du\/books\/images\/9781455570249.jpg","list_image_width":330,"list_image_height":466,"books":[{"age_group":"","amazon_product_url":"https:\/\/www.amazon.com\/Make-Your-Bed-Little-Things\/dp\/1455570249?tag=thenewyorktim-20","article_chapter_link":"","author":"William H McRaven","book_image":"https:\/\/s1.nyt.com\/du\/books\/images\/9781455570249.jpg","book_image_width":330,"book_image_height":466,"book_review_link":"","contributor":"by William H. McRaven","contributor_note":"","created_date":"2017-04-27 16:00:09","description":"","first_chapter_link":"","price":0,"primary_isbn10":"1455570249","primary_isbn13":"9781455570249","publisher":"Grand Central","rank":1,"rank_last_week":1,"sunday_review_link":"","title":"MAKE YOUR BED","updated_date":"2017-04-27 21:00:11","weeks_on_list":3,"buy_links":[{"name":"Local Booksellers","url":"http:\/\/www.indiebound.org\/book\/9781455570249?aff=NYT"},{"name":"Barnes and Noble","url":"http:\/\/www.anrdoezrs.net\/click-7990613-11819508?url=http%3A%2F%2Fwww.barnesandnoble.com%2Fw%2F%3Fean%3D9781455570249"},{"name":"Amazon","url":"https:\/\/www.amazon.com\/Make-Your-Bed-Little-Things\/dp\/1455570249?tag=thenewyorktim-20"}]},{"age_group":"","amazon_product_url":"http:\/\/www.amazon.com\/Subtle-Art-Not-Giving-Counterintuitive\/dp\/0062457713?tag=thenewyorktim-20","article_chapter_link":"","author":"Mark Manson","book_image":"https:\/\/s1.nyt.com\/du\/books\/images\/9780062457714.jpg","book_image_width":330,"book_image_height":495,"book_review_link":"","contributor":"by Mark Manson","contributor_note":"","created_date":"2017-04-27 16:00:09","description":"","first_chapter_link":"","price":0,"primary_isbn10":"0062457713","primary_isbn13":"9780062457714","publisher":"HarperOne\/HarperCollins","rank":2,"rank_last_week":3,"sunday_review_link":"","title":"THE SUBTLE ART OF NOT GIVING A ----------","updated_date":"2017-04-27 21:00:11","weeks_on_list":19,"buy_links":[{"name":"Local Booksellers","url":"http:\/\/www.indiebound.org\/book\/9780062457714?aff=NYT"},{"name":"Barnes and Noble","url":"http:\/\/www.anrdoezrs.net\/click-7990613-11819508?url=http%3A%2F%2Fwww.barnesandnoble.com%2Fw%2F%3Fean%3D9780062457714"},{"name":"Amazon","url":"http:\/\/www.amazon.com\/Subtle-Art-Not-Giving-Counterintuitive\/dp\/0062457713?tag=thenewyorktim-20"}]},{"age_group":"","amazon_product_url":"http:\/\/www.amazon.com\/You-Are-Badass-Doubting-Greatness-ebook\/dp\/B00B3M3VWS?tag=thenewyorktim-20","article_chapter_link":"","author":"Jen Sincero","book_image":"https:\/\/s1.nyt.com\/du\/books\/images\/9780762447695.jpg","book_image_width":315,"book_image_height":495,"book_review_link":"","contributor":"by Jen Sincero","contributor_note":"","created_date":"2017-04-27 16:00:09","description":"","first_chapter_link":"","price":0,"primary_isbn10":"0762447699","primary_isbn13":"9780762447695","publisher":"Running Press","rank":3,"rank_last_week":2,"sunday_review_link":"","title":"YOU ARE A BADASS","updated_date":"2017-04-27 21:00:11","weeks_on_list":67,"buy_links":[{"name":"Local Booksellers","url":"http:\/\/www.indiebound.org\/book\/9780762447695?aff=NYT"},{"name":"Barnes and Noble","url":"http:\/\/www.anrdoezrs.net\/click-7990613-11819508?url=http%3A%2F%2Fwww.barnesandnoble.com%2Fw%2F%3Fean%3D9780762447695"},{"name":"Amazon","url":"http:\/\/www.amazon.com\/You-Are-Badass-Doubting-Greatness-ebook\/dp\/B00B3M3VWS?tag=thenewyorktim-20"}]},{"age_group":"","amazon_product_url":"http:\/\/www.amazon.com\/The-Love-Languages-Secret-Lasts\/dp\/0802473156?tag=thenewyorktim-20","article_chapter_link":"","author":"Gary Chapman","book_image":"https:\/\/s1.nyt.com\/du\/books\/images\/9780802473158.jpg","book_image_width":268,"book_image_height":400,"book_review_link":"","contributor":"by Gary Chapman","contributor_note":"","created_date":"2017-04-27 16:00:09","description":"","first_chapter_link":"","price":0,"primary_isbn10":"080241270X","primary_isbn13":"9780802412706","publisher":"Northfield","rank":4,"rank_last_week":5,"sunday_review_link":"","title":"THE FIVE LOVE LANGUAGES","updated_date":"2017-04-27 21:00:11","weeks_on_list":197,"buy_links":[{"name":"Local Booksellers","url":"http:\/\/www.indiebound.org\/book\/9780802412706?aff=NYT"},{"name":"Barnes and Noble","url":"http:\/\/www.anrdoezrs.net\/click-7990613-11819508?url=http%3A%2F%2Fwww.barnesandnoble.com%2Fw%2F%3Fean%3D9780802412706"},{"name":"Amazon","url":"http:\/\/www.amazon.com\/The-Love-Languages-Secret-Lasts\/dp\/0802473156?tag=thenewyorktim-20"}]},{"age_group":"","amazon_product_url":"https:\/\/www.amazon.com\/You-Are-Badass-Making-Money\/dp\/0735222975?tag=thenewyorktim-20","article_chapter_link":"","author":"Jen Sincero","book_image":"https:\/\/s1.nyt.com\/du\/books\/images\/9780735222977.jpg","book_image_width":328,"book_image_height":495,"book_review_link":"","contributor":"by Jen Sincero","contributor_note":"","created_date":"2017-04-27 16:00:09","description":"","first_chapter_link":"","price":0,"primary_isbn10":"0735222975","primary_isbn13":"9780735222977","publisher":"Viking","rank":5,"rank_last_week":0,"sunday_review_link":"","title":"YOU ARE A BADASS AT MAKING MONEY","updated_date":"2017-04-27 21:00:11","weeks_on_list":1,"buy_links":[{"name":"Local Booksellers","url":"http:\/\/www.indiebound.org\/book\/9780735222977?aff=NYT"},{"name":"Barnes and Noble","url":"http:\/\/www.anrdoezrs.net\/click-7990613-11819508?url=http%3A%2F%2Fwww.barnesandnoble.com%2Fw%2F%3Fean%3D9780735222977"},{"name":"Amazon","url":"https:\/\/www.amazon.com\/You-Are-Badass-Making-Money\/dp\/0735222975?tag=thenewyorktim-20"}]}]},{"list_id":13,"list_name":"Childrens Middle Grade Hardcover","list_name_encoded":"childrens-middle-grade-hardcover","display_name":"Children\u2019s Middle Grade Hardcover","updated":"WEEKLY","list_image":"https:\/\/s1.nyt.com\/du\/books\/images\/9780375899881.jpg","list_image_width":329,"list_image_height":495,"books":[{"age_group":"","amazon_product_url":"http:\/\/www.amazon.com\/Wonder-R-J-Palacio-ebook\/dp\/B0051ANPZQ?tag=thenewyorktim-20","article_chapter_link":"","author":"R J Palacio","book_image":"https:\/\/s1.nyt.com\/du\/books\/images\/9780375899881.jpg","book_image_width":329,"book_image_height":495,"book_review_link":"","contributor":"by R. J. Palacio","contributor_note":"","created_date":"2017-04-27 16:00:07","description":"A boy with a facial deformity starts school.","first_chapter_link":"","price":0,"primary_isbn10":"0375869026","primary_isbn13":"9780375869020","publisher":"Knopf","rank":1,"rank_last_week":2,"sunday_review_link":"https:\/\/www.nytimes.com\/2012\/04\/08\/books\/review\/wonder-by-r-j-palacio.html","title":"WONDER","updated_date":"2017-04-27 21:00:07","weeks_on_list":89,"buy_links":[{"name":"Local Booksellers","url":"http:\/\/www.indiebound.org\/book\/9780375869020?aff=NYT"},{"name":"Barnes and Noble","url":"http:\/\/www.anrdoezrs.net\/click-7990613-11819508?url=http%3A%2F%2Fwww.barnesandnoble.com%2Fw%2F%3Fean%3D9780375869020"},{"name":"Amazon","url":"http:\/\/www.amazon.com\/Wonder-R-J-Palacio-ebook\/dp\/B0051ANPZQ?tag=thenewyorktim-20"}]},{"age_group":"","amazon_product_url":"https:\/\/www.amazon.com\/Dog-Man-Unleashed-Creator-Underpants\/dp\/0545935202?tag=thenewyorktim-20","article_chapter_link":"","author":"Dav Pilkey","book_image":"https:\/\/s1.nyt.com\/du\/books\/images\/9780545935203.jpg","book_image_width":330,"book_image_height":488,"book_review_link":"","contributor":"by Dav Pilkey","contributor_note":"","created_date":"2017-04-27 16:00:07","description":"Only one hybrid hero can foil the criminally minded, again.","first_chapter_link":"","price":0,"primary_isbn10":"0545935202","primary_isbn13":"9780545935203","publisher":"Scholastic","rank":2,"rank_last_week":1,"sunday_review_link":"","title":"DOG MAN UNLEASHED","updated_date":"2017-04-27 21:00:07","weeks_on_list":17,"buy_links":[{"name":"Local Booksellers","url":"http:\/\/www.indiebound.org\/book\/9780545935203?aff=NYT"},{"name":"Barnes and Noble","url":"http:\/\/www.anrdoezrs.net\/click-7990613-11819508?url=http%3A%2F%2Fwww.barnesandnoble.com%2Fw%2F%3Fean%3D9780545935203"},{"name":"Amazon","url":"https:\/\/www.amazon.com\/Dog-Man-Unleashed-Creator-Underpants\/dp\/0545935202?tag=thenewyorktim-20"}]},{"age_group":"","amazon_product_url":"http:\/\/www.amazon.com\/Dog-Man-Creator-Captain-Underpants-ebook\/dp\/B01B3DBA4C?tag=thenewyorktim-20","article_chapter_link":"","author":"Dav Pilkey","book_image":"https:\/\/s1.nyt.com\/du\/books\/images\/9780545581639.jpg","book_image_width":330,"book_image_height":487,"book_review_link":"","contributor":"by Dav Pilkey","contributor_note":"","created_date":"2017-04-27 16:00:07","description":"A dog\u2019s head is combined with a policeman\u2019s body to create this hybrid supercop hound.","first_chapter_link":"","price":0,"primary_isbn10":"0545581605","primary_isbn13":"9780545581608","publisher":"Scholastic","rank":3,"rank_last_week":3,"sunday_review_link":"","title":"DOG MAN","updated_date":"2017-04-27 21:00:07","weeks_on_list":34,"buy_links":[{"name":"Local Booksellers","url":"http:\/\/www.indiebound.org\/book\/9780545581608?aff=NYT"},{"name":"Barnes and Noble","url":"http:\/\/www.anrdoezrs.net\/click-7990613-11819508?url=http%3A%2F%2Fwww.barnesandnoble.com%2Fw%2F%3Fean%3D9780545581608"},{"name":"Amazon","url":"http:\/\/www.amazon.com\/Dog-Man-Creator-Captain-Underpants-ebook\/dp\/B01B3DBA4C?tag=thenewyorktim-20"}]},{"age_group":"","amazon_product_url":"https:\/\/www.amazon.com\/Beauty-Beast-Lost-Jennifer-Donnelly\/dp\/1484780981?tag=thenewyorktim-20","article_chapter_link":"","author":"Jennifer Donnelly","book_image":"https:\/\/s1.nyt.com\/du\/books\/images\/9781484780985.jpg","book_image_width":330,"book_image_height":488,"book_review_link":"","contributor":"by Jennifer Donnelly","contributor_note":"","created_date":"2017-04-27 16:00:07","description":"A volume in the Beast\u2019s library transports Belle to a tantalizing realm.","first_chapter_link":"","price":0,"primary_isbn10":"1484780981","primary_isbn13":"9781484780985","publisher":"Disney Press","rank":4,"rank_last_week":4,"sunday_review_link":"","title":"LOST IN A BOOK","updated_date":"2017-04-27 21:00:07","weeks_on_list":12,"buy_links":[{"name":"Local Booksellers","url":"http:\/\/www.indiebound.org\/book\/9781484780985?aff=NYT"},{"name":"Barnes and Noble","url":"http:\/\/www.anrdoezrs.net\/click-7990613-11819508?url=http%3A%2F%2Fwww.barnesandnoble.com%2Fw%2F%3Fean%3D9781484780985"},{"name":"Amazon","url":"https:\/\/www.amazon.com\/Beauty-Beast-Lost-Jennifer-Donnelly\/dp\/1484780981?tag=thenewyorktim-20"}]},{"age_group":"","amazon_product_url":"https:\/\/www.amazon.com\/Girl-Who-Drank-Moon\/dp\/1616205679?tag=thenewyorktim-20","article_chapter_link":"","author":"Kelly Barnhill","book_image":"https:\/\/s1.nyt.com\/du\/books\/images\/9781616205676.jpg","book_image_width":330,"book_image_height":495,"book_review_link":"https:\/\/www.nytimes.com\/2016\/10\/09\/books\/review\/girl-who-drank-the-moon-kelly-barnhill.html","contributor":"by Kelly Barnhill","contributor_note":"","created_date":"2017-04-27 16:00:07","description":"A sacrificial girl is saved by a good witch.","first_chapter_link":"","price":0,"primary_isbn10":"1616205679","primary_isbn13":"9781616205676","publisher":"Algonquin","rank":5,"rank_last_week":5,"sunday_review_link":"","title":"THE GIRL WHO DRANK THE MOON","updated_date":"2017-04-27 21:00:07","weeks_on_list":16,"buy_links":[{"name":"Local Booksellers","url":"http:\/\/www.indiebound.org\/book\/9781616205676?aff=NYT"},{"name":"Barnes and Noble","url":"http:\/\/www.anrdoezrs.net\/click-7990613-11819508?url=http%3A%2F%2Fwww.barnesandnoble.com%2Fw%2F%3Fean%3D9781616205676"},{"name":"Amazon","url":"https:\/\/www.amazon.com\/Girl-Who-Drank-Moon\/dp\/1616205679?tag=thenewyorktim-20"}]}]},{"list_id":7,"list_name":"Picture Books","list_name_encoded":"picture-books","display_name":"Children\u2019s Picture Books","updated":"WEEKLY","list_image":"https:\/\/s1.nyt.com\/du\/books\/images\/9780385376716.jpg","list_image_width":330,"list_image_height":347,"books":[{"age_group":"","amazon_product_url":"http:\/\/www.amazon.com\/The-Wonderful-Things-You-Will\/dp\/0385376715?tag=thenewyorktim-20","article_chapter_link":"","author":"Emily Winfield Martin","book_image":"https:\/\/s1.nyt.com\/du\/books\/images\/9780385376716.jpg","book_image_width":330,"book_image_height":347,"book_review_link":"","contributor":"by Emily Winfield Martin","contributor_note":"","created_date":"2017-04-27 16:00:10","description":"A celebration of future possibilities.","first_chapter_link":"","price":0,"primary_isbn10":"0385376715","primary_isbn13":"9780385376716","publisher":"Random House","rank":1,"rank_last_week":1,"sunday_review_link":"","title":"THE WONDERFUL THINGS YOU WILL BE","updated_date":"2017-04-27 21:00:12","weeks_on_list":82,"buy_links":[{"name":"Local Booksellers","url":"http:\/\/www.indiebound.org\/book\/9780385376716?aff=NYT"},{"name":"Barnes and Noble","url":"http:\/\/www.anrdoezrs.net\/click-7990613-11819508?url=http%3A%2F%2Fwww.barnesandnoble.com%2Fw%2F%3Fean%3D9780385376716"},{"name":"Amazon","url":"http:\/\/www.amazon.com\/The-Wonderful-Things-You-Will\/dp\/0385376715?tag=thenewyorktim-20"}]},{"age_group":"","amazon_product_url":"http:\/\/www.amazon.com\/Wish-You-More-Krouse-Rosenthal\/dp\/1452126992?tag=thenewyorktim-20","article_chapter_link":"","author":"Amy Krouse Rosenthal","book_image":"https:\/\/s1.nyt.com\/du\/books\/images\/9781452126999.jpg","book_image_width":330,"book_image_height":330,"book_review_link":"","contributor":"by Amy Krouse Rosenthal. Illustrated by Tom Lichtenheld","contributor_note":"Illustrated by Tom Lichtenheld","created_date":"2017-04-27 16:00:10","description":"A bounty of good wishes.","first_chapter_link":"","price":0,"primary_isbn10":"1452126992","primary_isbn13":"9781452126999","publisher":"Chronicle","rank":2,"rank_last_week":0,"sunday_review_link":"","title":"I WISH YOU MORE","updated_date":"2017-04-27 21:00:12","weeks_on_list":19,"buy_links":[{"name":"Local Booksellers","url":"http:\/\/www.indiebound.org\/book\/9781452126999?aff=NYT"},{"name":"Barnes and Noble","url":"http:\/\/www.anrdoezrs.net\/click-7990613-11819508?url=http%3A%2F%2Fwww.barnesandnoble.com%2Fw%2F%3Fean%3D9781452126999"},{"name":"Amazon","url":"http:\/\/www.amazon.com\/Wish-You-More-Krouse-Rosenthal\/dp\/1452126992?tag=thenewyorktim-20"}]},{"age_group":"","amazon_product_url":"http:\/\/www.amazon.com\/The-Crayons-Quit-Drew-Daywalt\/dp\/0399255370?tag=thenewyorktim-20","article_chapter_link":"","author":"Drew Daywalt","book_image":"https:\/\/s1.nyt.com\/du\/books\/images\/9780399255373.jpg","book_image_width":330,"book_image_height":332,"book_review_link":"","contributor":"by Drew Daywalt. Illustrated by Oliver Jeffers","contributor_note":"Illustrated by Oliver Jeffers","created_date":"2017-04-27 16:00:10","description":"Problems arise when Duncan\u2019s crayons revolt.","first_chapter_link":"","price":0,"primary_isbn10":"0399255370","primary_isbn13":"9780399255373","publisher":"Philomel","rank":3,"rank_last_week":4,"sunday_review_link":"https:\/\/www.nytimes.com\/2013\/08\/25\/books\/review\/henris-scissors-by-jeanette-winter-and-more.html","title":"THE DAY THE CRAYONS QUIT","updated_date":"2017-04-27 21:00:12","weeks_on_list":200,"buy_links":[{"name":"Local Booksellers","url":"http:\/\/www.indiebound.org\/book\/9780399255373?aff=NYT"},{"name":"Barnes and Noble","url":"http:\/\/www.anrdoezrs.net\/click-7990613-11819508?url=http%3A%2F%2Fwww.barnesandnoble.com%2Fw%2F%3Fean%3D9780399255373"},{"name":"Amazon","url":"http:\/\/www.amazon.com\/The-Crayons-Quit-Drew-Daywalt\/dp\/0399255370?tag=thenewyorktim-20"}]},{"age_group":"","amazon_product_url":"https:\/\/www.amazon.com\/Touch-Earth-Julian-Lennon\/dp\/1510720839?tag=thenewyorktim-20","article_chapter_link":"","author":"Julian Lennon with Bart Davis","book_image":"https:\/\/s1.nyt.com\/du\/books\/images\/9781510720831.jpg","book_image_width":330,"book_image_height":262,"book_review_link":"","contributor":"by Julian Lennon with Bart Davis. Illustrated by Smiljana Coh","contributor_note":"Illustrated by Smiljana Coh","created_date":"2017-04-27 16:00:10","description":"A magical plane can take you places you've never been.","first_chapter_link":"","price":0,"primary_isbn10":"1510720839","primary_isbn13":"9781510720831","publisher":"Sky Pony","rank":4,"rank_last_week":0,"sunday_review_link":"","title":"TOUCH THE EARTH","updated_date":"2017-04-27 21:00:12","weeks_on_list":1,"buy_links":[{"name":"Local Booksellers","url":"http:\/\/www.indiebound.org\/book\/9781510720831?aff=NYT"},{"name":"Barnes and Noble","url":"http:\/\/www.anrdoezrs.net\/click-7990613-11819508?url=http%3A%2F%2Fwww.barnesandnoble.com%2Fw%2F%3Fean%3D9781510720831"},{"name":"Amazon","url":"https:\/\/www.amazon.com\/Touch-Earth-Julian-Lennon\/dp\/1510720839?tag=thenewyorktim-20"}]},{"age_group":"","amazon_product_url":"http:\/\/www.amazon.com\/Dragons-Love-Tacos-Adam-Rubin\/dp\/0803736800?tag=thenewyorktim-20","article_chapter_link":"","author":"Adam Rubin","book_image":"https:\/\/s1.nyt.com\/du\/books\/images\/9780803736801.jpg","book_image_width":330,"book_image_height":330,"book_review_link":"","contributor":"by Adam Rubin. Illustrated by Daniel Salmieri","contributor_note":"Illustrated by Daniel Salmieri","created_date":"2017-04-27 16:00:10","description":"What to serve your dragon-guests.","first_chapter_link":"","price":0,"primary_isbn10":"0803736800","primary_isbn13":"9780803736801","publisher":"Dial","rank":5,"rank_last_week":5,"sunday_review_link":"","title":"DRAGONS LOVE TACOS","updated_date":"2017-04-27 21:00:12","weeks_on_list":166,"buy_links":[{"name":"Local Booksellers","url":"http:\/\/www.indiebound.org\/book\/9780803736801?aff=NYT"},{"name":"Barnes and Noble","url":"http:\/\/www.anrdoezrs.net\/click-7990613-11819508?url=http%3A%2F%2Fwww.barnesandnoble.com%2Fw%2F%3Fean%3D9780803736801"},{"name":"Amazon","url":"http:\/\/www.amazon.com\/Dragons-Love-Tacos-Adam-Rubin\/dp\/0803736800?tag=thenewyorktim-20"}]}]},{"list_id":10,"list_name":"Series Books","list_name_encoded":"series-books","display_name":"Children\u2019s Series","updated":"WEEKLY","list_image":"https:\/\/s1.nyt.com\/du\/books\/images\/9780590353427.jpg","list_image_width":328,"list_image_height":495,"books":[{"age_group":"","amazon_product_url":"http:\/\/www.amazon.com\/Harry-Potter-And-Order-Phoenix\/dp\/0439358078?tag=thenewyorktim-20","article_chapter_link":"","author":"J K Rowling","book_image":"https:\/\/s1.nyt.com\/du\/books\/images\/9780590353427.jpg","book_image_width":328,"book_image_height":495,"book_review_link":"","contributor":"by J. K. Rowling","contributor_note":"","created_date":"2017-04-27 16:00:06","description":"A wizard hones his conjuring skills in the service of fighting evil.","first_chapter_link":"","price":0,"primary_isbn10":"1338099132","primary_isbn13":"9781338099133","publisher":"Scholastic","rank":1,"rank_last_week":1,"sunday_review_link":"","title":"HARRY POTTER","updated_date":"2017-04-27 21:00:07","weeks_on_list":422,"buy_links":[{"name":"Local Booksellers","url":"http:\/\/www.indiebound.org\/book\/9781338099133?aff=NYT"},{"name":"Barnes and Noble","url":"http:\/\/www.anrdoezrs.net\/click-7990613-11819508?url=http%3A%2F%2Fwww.barnesandnoble.com%2Fw%2F%3Fean%3D9781338099133"},{"name":"Amazon","url":"http:\/\/www.amazon.com\/Harry-Potter-And-Order-Phoenix\/dp\/0439358078?tag=thenewyorktim-20"}]},{"age_group":"","amazon_product_url":"http:\/\/www.amazon.com\/Diary-Wimpy-Kid-Hard-Luck\/dp\/1419711326?tag=thenewyorktim-20","article_chapter_link":"","author":"Jeff Kinney","book_image":"https:\/\/s1.nyt.com\/du\/books\/images\/9781419711329.jpg","book_image_width":330,"book_image_height":484,"book_review_link":"","contributor":"written and illustrated by Jeff Kinney","contributor_note":"written and illustrated by Jeff Kinney","created_date":"2017-04-27 16:00:06","description":"The travails and challenges of adolescence.","first_chapter_link":"","price":0,"primary_isbn10":"1419723448","primary_isbn13":"9781419723445","publisher":"Amulet","rank":2,"rank_last_week":2,"sunday_review_link":"","title":"DIARY OF A WIMPY KID","updated_date":"2017-04-27 21:00:07","weeks_on_list":423,"buy_links":[{"name":"Local Booksellers","url":"http:\/\/www.indiebound.org\/book\/9781419723445?aff=NYT"},{"name":"Barnes and Noble","url":"http:\/\/www.anrdoezrs.net\/click-7990613-11819508?url=http%3A%2F%2Fwww.barnesandnoble.com%2Fw%2F%3Fean%3D9781419723445"},{"name":"Amazon","url":"http:\/\/www.amazon.com\/Diary-Wimpy-Kid-Hard-Luck\/dp\/1419711326?tag=thenewyorktim-20"}]},{"age_group":"","amazon_product_url":"http:\/\/www.amazon.com\/Library-Souls-Peregrines-Peculiar-Children\/dp\/159474758X?tag=thenewyorktim-20","article_chapter_link":"","author":"Ransom Riggs","book_image":"https:\/\/s1.nyt.com\/du\/books\/images\/9781594747588.jpg","book_image_width":160,"book_image_height":248,"book_review_link":"","contributor":"by Ransom Riggs","contributor_note":"","created_date":"2017-04-27 16:00:06","description":"Time travelers try to save their headmistress.","first_chapter_link":"","price":0,"primary_isbn10":"1594749310","primary_isbn13":"9781594749315","publisher":"Quirk\/Penguin","rank":3,"rank_last_week":3,"sunday_review_link":"","title":"MISS PEREGRINE\u2019S PECULIAR CHILDREN","updated_date":"2017-04-27 21:00:07","weeks_on_list":83,"buy_links":[{"name":"Local Booksellers","url":"http:\/\/www.indiebound.org\/book\/9781594749315?aff=NYT"},{"name":"Barnes and Noble","url":"http:\/\/www.anrdoezrs.net\/click-7990613-11819508?url=http%3A%2F%2Fwww.barnesandnoble.com%2Fw%2F%3Fean%3D9781594749315"},{"name":"Amazon","url":"http:\/\/www.amazon.com\/Library-Souls-Peregrines-Peculiar-Children\/dp\/159474758X?tag=thenewyorktim-20"}]},{"age_group":"","amazon_product_url":"http:\/\/www.amazon.com\/Dork-Diaries-Tales-Not-So-Glam-Star\/dp\/1442487674?tag=thenewyorktim-20","article_chapter_link":"","author":"Rachel Ren\u00e9e Russell","book_image":"https:\/\/s1.nyt.com\/du\/books\/images\/9781442487673.jpg","book_image_width":330,"book_image_height":480,"book_review_link":"","contributor":"by Rachel Ren\u00e9e Russell","contributor_note":"","created_date":"2017-04-27 16:00:06","description":"Nikki Maxwell navigates the halls of middle school.","first_chapter_link":"","price":0,"primary_isbn10":"1481479202","primary_isbn13":"9781481479202","publisher":"Simon & Schuster","rank":4,"rank_last_week":6,"sunday_review_link":"","title":"DORK DIARIES","updated_date":"2017-04-27 21:00:07","weeks_on_list":204,"buy_links":[{"name":"Local Booksellers","url":"http:\/\/www.indiebound.org\/book\/9781481479202?aff=NYT"},{"name":"Barnes and Noble","url":"http:\/\/www.anrdoezrs.net\/click-7990613-11819508?url=http%3A%2F%2Fwww.barnesandnoble.com%2Fw%2F%3Fean%3D9781481479202"},{"name":"Amazon","url":"http:\/\/www.amazon.com\/Dork-Diaries-Tales-Not-So-Glam-Star\/dp\/1442487674?tag=thenewyorktim-20"}]},{"age_group":"","amazon_product_url":"http:\/\/www.amazon.com\/Princess-Black-Hungry-Bunny-Horde\/dp\/0763665134?tag=thenewyorktim-20","article_chapter_link":"","author":"Shannon Hale and Dean Hale","book_image":"https:\/\/s1.nyt.com\/du\/books\/images\/9780763665135.jpg","book_image_width":330,"book_image_height":423,"book_review_link":"","contributor":"by Shannon Hale and Dean Hale. Illustrated by LeUyen Pham","contributor_note":"Illustrated by LeUyen Pham","created_date":"2017-04-27 16:00:06","description":"Magnolia summons her superhero secret identity when the kingdom needs her help.","first_chapter_link":"","price":0,"primary_isbn10":"0763678880","primary_isbn13":"9780763678883","publisher":"Candlewick","rank":5,"rank_last_week":8,"sunday_review_link":"https:\/\/www.nytimes.com\/2014\/11\/09\/books\/review\/pennyroyal-academy-and-the-princess-in-black.html","title":"PRINCESS IN BLACK","updated_date":"2017-04-27 21:00:07","weeks_on_list":8,"buy_links":[{"name":"Local Booksellers","url":"http:\/\/www.indiebound.org\/book\/9780763678883?aff=NYT"},{"name":"Barnes and Noble","url":"http:\/\/www.anrdoezrs.net\/click-7990613-11819508?url=http%3A%2F%2Fwww.barnesandnoble.com%2Fw%2F%3Fean%3D9780763678883"},{"name":"Amazon","url":"http:\/\/www.amazon.com\/Princess-Black-Hungry-Bunny-Horde\/dp\/0763665134?tag=thenewyorktim-20"}]}]},{"list_id":14,"list_name":"Young Adult Hardcover","list_name_encoded":"young-adult-hardcover","display_name":"Young Adult Hardcover","updated":"WEEKLY","list_image":"https:\/\/s1.nyt.com\/du\/books\/images\/9781595141880.jpg","list_image_width":185,"list_image_height":278,"books":[{"age_group":"","amazon_product_url":"http:\/\/www.amazon.com\/Thirteen-Reasons-Why-Jay-Asher\/dp\/159514188X?tag=thenewyorktim-20","article_chapter_link":"","author":"Jay Asher","book_image":"https:\/\/s1.nyt.com\/du\/books\/images\/9781595141880.jpg","book_image_width":185,"book_image_height":278,"book_review_link":"","contributor":"by Jay Asher","contributor_note":"","created_date":"2017-04-27 16:00:07","description":"After Clay's crush kills herself, cassettes arrive at his doorstep enumerating the reasons.","first_chapter_link":"","price":0,"primary_isbn10":"1595147888","primary_isbn13":"9781595147882","publisher":"Razorbill","rank":1,"rank_last_week":1,"sunday_review_link":"","title":"THIRTEEN REASONS WHY","updated_date":"2017-04-27 21:00:08","weeks_on_list":3,"buy_links":[{"name":"Local Booksellers","url":"http:\/\/www.indiebound.org\/book\/9781595147882?aff=NYT"},{"name":"Barnes and Noble","url":"http:\/\/www.anrdoezrs.net\/click-7990613-11819508?url=http%3A%2F%2Fwww.barnesandnoble.com%2Fw%2F%3Fean%3D9781595147882"},{"name":"Amazon","url":"http:\/\/www.amazon.com\/Thirteen-Reasons-Why-Jay-Asher\/dp\/159514188X?tag=thenewyorktim-20"}]},{"age_group":"","amazon_product_url":"https:\/\/www.amazon.com\/Hate-U-Give-Angie-Thomas\/dp\/0062498533?tag=thenewyorktim-20","article_chapter_link":"","author":"Angie Thomas","book_image":"https:\/\/s1.nyt.com\/du\/books\/images\/9780062498533.jpg","book_image_width":328,"book_image_height":495,"book_review_link":"","contributor":"by Angie Thomas","contributor_note":"","created_date":"2017-04-27 16:00:07","description":"A 16-year-old girl sees a police officer kill her friend.","first_chapter_link":"","price":0,"primary_isbn10":"0062498533","primary_isbn13":"9780062498533","publisher":"Balzer & Bray","rank":2,"rank_last_week":3,"sunday_review_link":"","title":"THE HATE U GIVE","updated_date":"2017-04-27 21:00:08","weeks_on_list":8,"buy_links":[{"name":"Local Booksellers","url":"http:\/\/www.indiebound.org\/book\/9780062498533?aff=NYT"},{"name":"Barnes and Noble","url":"http:\/\/www.anrdoezrs.net\/click-7990613-11819508?url=http%3A%2F%2Fwww.barnesandnoble.com%2Fw%2F%3Fean%3D9780062498533"},{"name":"Amazon","url":"https:\/\/www.amazon.com\/Hate-U-Give-Angie-Thomas\/dp\/0062498533?tag=thenewyorktim-20"}]},{"age_group":"","amazon_product_url":"https:\/\/www.amazon.com\/Alex-Eliza-Story-Melissa-Cruz\/dp\/1524739626?tag=thenewyorktim-20","article_chapter_link":"","author":"Melissa de la Cruz","book_image":"https:\/\/s1.nyt.com\/du\/books\/images\/9781524739621.jpg","book_image_width":328,"book_image_height":495,"book_review_link":"","contributor":"by Melissa de la Cruz","contributor_note":"","created_date":"2017-04-27 16:00:07","description":"As the Revolution unfolds, Eliza Schuyler meets a man named Hamilton.","first_chapter_link":"","price":0,"primary_isbn10":"1524739626","primary_isbn13":"9781524739621","publisher":"Putnam","rank":3,"rank_last_week":2,"sunday_review_link":"","title":"ALEX AND ELIZA","updated_date":"2017-04-27 21:00:08","weeks_on_list":2,"buy_links":[{"name":"Local Booksellers","url":"http:\/\/www.indiebound.org\/book\/9781524739621?aff=NYT"},{"name":"Barnes and Noble","url":"http:\/\/www.anrdoezrs.net\/click-7990613-11819508?url=http%3A%2F%2Fwww.barnesandnoble.com%2Fw%2F%3Fean%3D9781524739621"},{"name":"Amazon","url":"https:\/\/www.amazon.com\/Alex-Eliza-Story-Melissa-Cruz\/dp\/1524739626?tag=thenewyorktim-20"}]},{"age_group":"","amazon_product_url":"http:\/\/www.amazon.com\/This-Is-Where-It-Ends\/dp\/149262246X?tag=thenewyorktim-20","article_chapter_link":"","author":"Marieke Nijkamp","book_image":"https:\/\/s1.nyt.com\/du\/books\/images\/9781492622468.jpg","book_image_width":328,"book_image_height":495,"book_review_link":"","contributor":"by Marieke Nijkamp","contributor_note":"","created_date":"2017-04-27 16:00:07","description":"An act of violence parsed from four perspectives.","first_chapter_link":"","price":0,"primary_isbn10":"149262246X","primary_isbn13":"9781492622468","publisher":"Sourcebooks Fire","rank":4,"rank_last_week":6,"sunday_review_link":"","title":"THIS IS WHERE IT ENDS","updated_date":"2017-04-27 21:00:08","weeks_on_list":47,"buy_links":[{"name":"Local Booksellers","url":"http:\/\/www.indiebound.org\/book\/9781492622468?aff=NYT"},{"name":"Barnes and Noble","url":"http:\/\/www.anrdoezrs.net\/click-7990613-11819508?url=http%3A%2F%2Fwww.barnesandnoble.com%2Fw%2F%3Fean%3D9781492622468"},{"name":"Amazon","url":"http:\/\/www.amazon.com\/This-Is-Where-It-Ends\/dp\/149262246X?tag=thenewyorktim-20"}]},{"age_group":"","amazon_product_url":"https:\/\/www.amazon.com\/Carve-Mark-Veronica-Roth\/dp\/0062348639?tag=thenewyorktim-20","article_chapter_link":"","author":"Veronica Roth","book_image":"https:\/\/s1.nyt.com\/du\/books\/images\/9780062348630.jpg","book_image_width":328,"book_image_height":495,"book_review_link":"","contributor":"by Veronica Roth","contributor_note":"","created_date":"2017-04-27 16:00:07","description":"An oracle's son is able to stop the painful flow of Cyra's powers.","first_chapter_link":"","price":0,"primary_isbn10":"0062348639","primary_isbn13":"9780062348630","publisher":"Katherine Tegen","rank":5,"rank_last_week":4,"sunday_review_link":"","title":"CARVE THE MARK","updated_date":"2017-04-27 21:00:08","weeks_on_list":14,"buy_links":[{"name":"Local Booksellers","url":"http:\/\/www.indiebound.org\/book\/9780062348630?aff=NYT"},{"name":"Barnes and Noble","url":"http:\/\/www.anrdoezrs.net\/click-7990613-11819508?url=http%3A%2F%2Fwww.barnesandnoble.com%2Fw%2F%3Fean%3D9780062348630"},{"name":"Amazon","url":"https:\/\/www.amazon.com\/Carve-Mark-Veronica-Roth\/dp\/0062348639?tag=thenewyorktim-20"}]}]}]}}
